{
  "name": "Perci Cognitive Weights \u00b7 Bitwork Transcendence",
  "version": 3,
  "format": "PERCIW03",
  "architecture": "4096-bit sparse associative Bitwork network with signed expert evidence and weight-resident concepts",
  "size_bytes": 200425696,
  "size_mib": 191.14083862304688,
  "prototype_count": 385308,
  "concept_count": 100,
  "bits_per_activation": 4096,
  "words_per_activation": 64,
  "labels": [
    "greeting",
    "identity",
    "english",
    "logic",
    "math",
    "geometry",
    "memory",
    "code",
    "governance",
    "planning",
    "explanation",
    "systems",
    "science",
    "creativity",
    "comparison",
    "general"
  ],
  "record_size": 520,
  "generated_record_count": 800000,
  "deduplicated_record_count": 414692,
  "deduplication_ratio": 0.518365,
  "label_record_counts": {
    "greeting": 600,
    "identity": 691,
    "english": 28407,
    "logic": 30377,
    "math": 35393,
    "geometry": 32157,
    "memory": 1957,
    "code": 28270,
    "governance": 27179,
    "planning": 27934,
    "explanation": 28242,
    "systems": 28153,
    "science": 27986,
    "creativity": 28653,
    "comparison": 28415,
    "general": 30894
  },
  "label_concept_counts": {
    "greeting": 4,
    "identity": 5,
    "english": 6,
    "logic": 6,
    "math": 5,
    "geometry": 18,
    "memory": 5,
    "code": 5,
    "governance": 5,
    "planning": 5,
    "explanation": 5,
    "systems": 6,
    "science": 7,
    "creativity": 5,
    "comparison": 5,
    "general": 8
  },
  "sha256": "ff9985d730db8249168488574a79a507ba84ec97170f954d0a85191d0bc7c796",
  "corpus_sha256": "bfca7bae33e5cbe81ad3e63dd4e9d042302c7434bfdce21bafaffe0625fb6a16",
  "seed": 5784119745374541363,
  "build_seconds": 347.979,
  "maximum_size_bytes": 209715200,
  "automatic_promotion": false,
  "limitations": [
    "Not a transformer or general-purpose pretrained language model.",
    "Weight-resident insights are bounded conceptual priors selected by associative geometry.",
    "Exact arithmetic and geometry remain delegated to deterministic tools.",
    "Larger size is not accepted as greater cognition without held-out transfer evidence.",
    "Promotion requires comparison with the active v0.2 model and explicit authorization."
  ]
}
